main.py
queryweathermcp-1.0.0.dist-info/METADATA
queryweathermcp-1.0.0.dist-info/WHEEL
queryweathermcp-1.0.0.dist-info/entry_points.txt
queryweathermcp-1.0.0.dist-info/top_level.txt
queryweathermcp-1.0.0.dist-info/RECORD
