Metadata-Version: 2.4
Name: queryweathermcp
Version: 1.0.0
Summary: 有时可以用的天气查询mcp
Requires-Python: >=3.11
Requires-Dist: build>=1.3.0
Requires-Dist: fastmcp>=2.11.2
Requires-Dist: httpx>=0.27.0
